ech/__init__.py
ech/__main__.py
ech/aws.py
ech/profile.py
ech/ssh.py
ech-0.1.1.dist-info/METADATA
ech-0.1.1.dist-info/WHEEL
ech-0.1.1.dist-info/entry_points.txt
ech-0.1.1.dist-info/top_level.txt
ech-0.1.1.dist-info/RECORD
