Metadata-Version: 2.1
Name: ech
Version: 0.1.1
Summary: Yet another simple AWS EC2 Tools
Author-email: Tom Shen <me@tomshen.io>
Project-URL: Homepage, https://github.com/tsunrise/ech
Classifier: Programming Language :: Python :: 3
Classifier: License :: OSI Approved :: MIT License
Classifier: Development Status :: 3 - Alpha
Classifier: Environment :: Console
Requires-Python: >=3.7
Requires-Dist: sshconf
Requires-Dist: boto3
Requires-Dist: toml
Requires-Dist: colorama
